{
    "active_user_count": 16, 
    "advertiser_category": null, 
    "audience_target": "", 
    "avg_comment_num_per_submission": 2, 
    "avg_submission_score": 6, 
    "collection_range_end_unix_timestamp": 1506816000, 
    "collection_range_end_utc": "2017-10-01 00:00:00", 
    "collection_range_start_unix_timestamp": 1504224000, 
    "collection_range_start_utc": "2017-09-01 00:00:00", 
    "description": "#Visualization\n\nFor topics related to information visualization and the design of graphs, charts, maps, etc.\n\nPost guides, tutorials, and discussion threads about information visualization.\n\nWe also welcome posts including visualization works-in-progress and requests for critiques.\n\n#Posting rules\n\nBe polite and constructive when posting in this subreddit. Posts and comments that are rude, harassing, sexist, racist, etc. will be removed and may result in a ban.\n\n---\n\nWhile posts linking to finished information visualizations are allowed, we encourage sharing visualizations only when they will lead to discussion about the design and construction of the visualization.\n\nSee the Related Subreddits section below for more appropriate places to share finished work.\n\n---\n\nDo NOT post sales, memes, cute pictures, jokes, etc. Repeated offenses of this rule will result in a ban.\n\n---\n\nPlease report any submissions or comments violating these rules using the report button.\n\n#Related Subreddits\n\nIf you want to post something related to information visualization but it doesn't fit the criteria above, consider posting to one of the following subreddits.\n\n* [DataIsBeautiful](/r/dataisbeautiful): Share data visualizations\n\n* [MapPorn](/r/mapporn): Share maps, map visualizations, etc.\n\n* [Infographics](/r/Infographics): Share infographics and other unautomated diagrams\n\n* [WordCloud](/r/wordcloud): Specifically for sharing word clouds\n\n* [DataVizRequests](/r/DataVizRequests): Request a visualization to be made\n\n* [Tableau](/r/tableau): Share and discuss visualizations made with Tableau software\n\n* [DataSets](/r/datasets): Request and share data sets\n\n* [SampleSize](/r/SampleSize): Conduct and share surveys\n\n* [DataIsUgly](/r/dataisugly): Share poorly designed information visualizations\n\n* [FunnyCharts](/r/FunnyCharts): Share funny graphs and charts\n\n* [MathPics](/r/mathpics): Share pictures and visualizations of mathematical concepts\n\n* [RedactedCharts](/r/RedactedCharts): Try to guess what a chart is about without the labels\n\n* [Statistics](/r/statistics): For all questions and articles related to statistics", 
    "display_name": "visualization", 
    "domain_occurrences": {
        "abc.net.au": 1, 
        "blog.sicara.com": 1, 
        "community.jmp.com": 1, 
        "content.pivotal.io": 1, 
        "dataquest.io": 1, 
        "datavizcatalogue.com": 1, 
        "imgur.com": 2, 
        "juanosborne.com": 1, 
        "kaggle.com": 1, 
        "medium.com": 1, 
        "reactdom.com": 1, 
        "sandipanweb.wordpress.com": 1, 
        "self.visualization": 12, 
        "srcole.github.io": 1, 
        "srushtiviz.com": 1, 
        "tehcookies.com": 1, 
        "twosixlabs.com": 1, 
        "visual.ly": 2, 
        "visualisingdata.com": 4, 
        "webdatarocks.com": 1, 
        "youtu.be": 5, 
        "youtube.com": 3
    }, 
    "id": "2qhn4", 
    "num_external_website_posts": 32, 
    "num_text_posts": 12, 
    "public_description": "For topics related to information visualization and the design of graphs, charts, maps, etc.", 
    "submissions": [
        {
            "author": "ATKS", 
            "created_utc": 1506620802.0, 
            "domain": "webdatarocks.com", 
            "id": "731rjw", 
            "is_reddit_media_domain": false, 
            "is_self": false, 
            "is_video": false, 
            "link_flair_css_class": null, 
            "link_flair_text": null, 
            "media": null, 
            "num_comments": 0, 
            "num_crossposts": 0, 
            "permalink": "/r/visualization/comments/731rjw/try_free_reporting_tool_to_visualize_complex_data/", 
            "score": 2, 
            "selftext": "", 
            "subreddit": "visualization", 
            "title": "Try Free Reporting Tool to visualize complex data. Well-designed Pivot Grid with enterprise features for real business. See Beta Version:", 
            "url": "https://www.webdatarocks.com/demos/javascript-pivot-table-demo/"
        }, 
        {
            "author": "Tsikhanenka", 
            "created_utc": 1506610196.0, 
            "domain": "youtu.be", 
            "id": "730kdp", 
            "is_reddit_media_domain": false, 
            "is_self": false, 
            "is_video": false, 
            "link_flair_css_class": null, 
            "link_flair_text": null, 
            "media": {
                "oembed": {
                    "author_name": "Skybuffer AS", 
                    "author_url": "https://www.youtube.com/channel/UCoLHhV2YNRGOgOlyl2tW3KA", 
                    "height": 338, 
                    "html": "<iframe width=\"600\" height=\"338\" src=\"https://www.youtube.com/embed/pFwiaQAyyjg?feature=oembed\" frameborder=\"0\" allowfullscreen></iframe>", 
                    "provider_name": "YouTube", 
                    "provider_url": "https://www.youtube.com/", 
                    "thumbnail_height": 360, 
                    "thumbnail_url": "https://i.ytimg.com/vi/pFwiaQAyyjg/hqdefault.jpg", 
                    "thumbnail_width": 480, 
                    "title": "/SKYBFR/ :: SAP Lumira 2.0 for Soccer Manager", 
                    "type": "video", 
                    "version": "1.0", 
                    "width": 600
                }, 
                "type": "youtube.com"
            }, 
            "num_comments": 0, 
            "num_crossposts": 0, 
            "permalink": "/r/visualization/comments/730kdp/is_it_possible_that_sport_trainers_rely_on/", 
            "score": 0, 
            "selftext": "", 
            "subreddit": "visualization", 
            "title": "Is it possible that Sport Trainers rely on analytics dashboards?", 
            "url": "https://youtu.be/pFwiaQAyyjg"
        }, 
        {
            "author": "DoubleTroubleBP", 
            "created_utc": 1506594486.0, 
            "domain": "imgur.com", 
            "id": "72z7kp", 
            "is_reddit_media_domain": false, 
            "is_self": false, 
            "is_video": false, 
            "link_flair_css_class": null, 
            "link_flair_text": null, 
            "media": null, 
            "num_comments": 4, 
            "num_crossposts": 0, 
            "permalink": "/r/visualization/comments/72z7kp/i_let_my_creativity_flow_to_overcome_a_blockade/", 
            "score": 7, 
            "selftext": "", 
            "subreddit": "visualization", 
            "title": "I let my creativity flow to overcome a blockade &ndash; and this is what I got", 
            "url": "https://imgur.com/nzYgYVI"
        }, 
        {
            "author": "xangg", 
            "created_utc": 1506533506.0, 
            "domain": "community.jmp.com", 
            "id": "72tv1i", 
            "is_reddit_media_domain": false, 
            "is_self": false, 
            "is_video": false, 
            "link_flair_css_class": null, 
            "link_flair_text": null, 
            "media": null, 
            "num_comments": 1, 
            "num_crossposts": 0, 
            "permalink": "/r/visualization/comments/72tv1i/the_packed_bars_chart_type_applying_focuscontext/", 
            "score": 1, 
            "selftext": "", 
            "subreddit": "visualization", 
            "title": "The packed bars chart type, applying Focus+Context to bar charts for data with many levels and skewed values [OC]", 
            "url": "https://community.jmp.com/t5/JMP-Blog/Introducing-packed-bars-a-new-chart-form/ba-p/39972"
        }, 
        {
            "author": "rino_design", 
            "created_utc": 1506530460.0, 
            "domain": "datavizcatalogue.com", 
            "id": "72tibw", 
            "is_reddit_media_domain": false, 
            "is_self": false, 
            "is_video": false, 
            "link_flair_css_class": null, 
            "link_flair_text": null, 
            "media": null, 
            "num_comments": 4, 
            "num_crossposts": 0, 
            "permalink": "/r/visualization/comments/72tibw/heres_some_unusual_box_plot_variations_you_might/", 
            "score": 29, 
            "selftext": "", 
            "subreddit": "visualization", 
            "title": "Here's some unusual Box Plot variations you might not know about...", 
            "url": "http://datavizcatalogue.com/blog/box-plot-variations/"
        }, 
        {
            "author": "kpei1hunnit", 
            "created_utc": 1506448340.0, 
            "domain": "imgur.com", 
            "id": "72m3tl", 
            "is_reddit_media_domain": false, 
            "is_self": false, 
            "is_video": false, 
            "link_flair_css_class": null, 
            "link_flair_text": null, 
            "media": {
                "oembed": {
                    "description": "Imgur: The most awesome images on the Internet.", 
                    "height": 550, 
                    "html": "<iframe class=\"embedly-embed\" src=\"//cdn.embedly.com/widgets/media.html?src=%2F%2Fimgur.com%2Fa%2F6JhTt%2Fembed&url=https%3A%2F%2Fimgur.com%2Fa%2F6JhTt&image=https%3A%2F%2Fi.imgur.com%2FwsOJdIg.jpg%3Ffb&key=522baf40bd3911e08d854040d3dc5c07&type=text%2Fhtml&schema=imgur\" width=\"550\" height=\"550\" scrolling=\"no\" frameborder=\"0\" allowfullscreen></iframe>", 
                    "provider_name": "Imgur", 
                    "provider_url": "http://imgur.com", 
                    "thumbnail_height": 315, 
                    "thumbnail_url": "https://i.imgur.com/wsOJdIg.jpg?fb", 
                    "thumbnail_width": 600, 
                    "title": "Heatmaps of Attacking Frequency", 
                    "type": "rich", 
                    "version": "1.0", 
                    "width": 550
                }, 
                "type": "imgur.com"
            }, 
            "num_comments": 5, 
            "num_crossposts": 0, 
            "permalink": "/r/visualization/comments/72m3tl/a_heatmap_of_counterstrike_players_positioning/", 
            "score": 29, 
            "selftext": "", 
            "subreddit": "visualization", 
            "title": "A Heatmap of Counter-Strike Player's Positioning over 1000 recorded Matchmaking games [OC]", 
            "url": "https://imgur.com/a/6JhTt"
        }, 
        {
            "author": "infinite-Joy", 
            "created_utc": 1506355970.0, 
            "domain": "medium.com", 
            "id": "72dgkw", 
            "is_reddit_media_domain": false, 
            "is_self": false, 
            "is_video": false, 
            "link_flair_css_class": null, 
            "link_flair_text": null, 
            "media": null, 
            "num_comments": 0, 
            "num_crossposts": 0, 
            "permalink": "/r/visualization/comments/72dgkw/grim_stats_through_the_prism_of_google_facets/", 
            "score": 3, 
            "selftext": "", 
            "subreddit": "visualization", 
            "title": "Grim Stats Through The Prism Of Google Facets", 
            "url": "https://medium.com/@joydeepubuntu/suicides-in-india-757634eab7f1"
        }, 
        {
            "author": "fl4v1", 
            "created_utc": 1506349622.0, 
            "domain": "blog.sicara.com", 
            "id": "72cr8t", 
            "is_reddit_media_domain": false, 
            "is_self": false, 
            "is_video": false, 
            "link_flair_css_class": null, 
            "link_flair_text": null, 
            "media": null, 
            "num_comments": 0, 
            "num_crossposts": 0, 
            "permalink": "/r/visualization/comments/72cr8t/importing_a_jupyter_notebook_in_another_to/", 
            "score": 6, 
            "selftext": "", 
            "subreddit": "visualization", 
            "title": "Importing a Jupyter notebook in another to present your results", 
            "url": "https://blog.sicara.com/present-data-science-results-jupyter-notebook-import-into-another-108433bc8505"
        }, 
        {
            "author": "belvitabiscuit", 
            "created_utc": 1506293784.0, 
            "domain": "self.visualization", 
            "id": "728h4k", 
            "is_reddit_media_domain": false, 
            "is_self": true, 
            "is_video": false, 
            "link_flair_css_class": null, 
            "link_flair_text": null, 
            "media": null, 
            "num_comments": 5, 
            "num_crossposts": 0, 
            "permalink": "/r/visualization/comments/728h4k/bls_stackedcross_section_bar_chart/", 
            "score": 2, 
            "selftext": "I was looking at some Bureau of Labor (BLS) statistics and came across [this chart on slide 3](https://www.bls.gov/iif/oshwc/osh/os/osch0049.pdf). Do these type of charts have a specific name? How can I create one of these in excel in a pragmatic manner (meaning, not having to manually insert shapes). If it is not practical to make in excel, can you recommend an alternative program or an alternative example?", 
            "subreddit": "visualization", 
            "title": "BLS: Stacked/Cross Section Bar Chart", 
            "url": "https://www.reddit.com/r/visualization/comments/728h4k/bls_stackedcross_section_bar_chart/"
        }, 
        {
            "author": "SandipanDeyUMBC", 
            "created_utc": 1506063051.0, 
            "domain": "sandipanweb.wordpress.com", 
            "id": "71pbg1", 
            "is_reddit_media_domain": false, 
            "is_self": false, 
            "is_video": false, 
            "link_flair_css_class": null, 
            "link_flair_text": null, 
            "media": null, 
            "num_comments": 0, 
            "num_crossposts": 0, 
            "permalink": "/r/visualization/comments/71pbg1/some_more_social_network_analysis_with_python/", 
            "score": 13, 
            "selftext": "", 
            "subreddit": "visualization", 
            "title": "Some more Social Network Analysis with Python", 
            "url": "https://sandipanweb.wordpress.com/2017/09/22/some-more-social-network-analysis-with-python/"
        }, 
        {
            "author": "person_ergo", 
            "created_utc": 1506005920.0, 
            "domain": "self.visualization", 
            "id": "71jocf", 
            "is_reddit_media_domain": false, 
            "is_self": true, 
            "is_video": false, 
            "link_flair_css_class": null, 
            "link_flair_text": null, 
            "media": null, 
            "num_comments": 3, 
            "num_crossposts": 0, 
            "permalink": "/r/visualization/comments/71jocf/visualization_name_requestinfo/", 
            "score": 5, 
            "selftext": "Hey everyone. Anyone know what the name of this chart is? https://www.washingtonpost.com/graphics/politics/2016-election/urban-rural-vote-swing/?hpid=hp_no-name_graphic-story-a%3Ahomepage%2Fstory  \nI feel like it should be called a swing chart and I think it's pretty cool. I've never seen it before today  \n  \nIt looks like it was rendered in Adobe Illustrated using ai2html", 
            "subreddit": "visualization", 
            "title": "Visualization Name Request/Info", 
            "url": "https://www.reddit.com/r/visualization/comments/71jocf/visualization_name_requestinfo/"
        }, 
        {
            "author": "MrAmelia", 
            "created_utc": 1505966282.0, 
            "domain": "self.visualization", 
            "id": "71gnlr", 
            "is_reddit_media_domain": false, 
            "is_self": true, 
            "is_video": false, 
            "link_flair_css_class": null, 
            "link_flair_text": null, 
            "media": null, 
            "num_comments": 1, 
            "num_crossposts": 0, 
            "permalink": "/r/visualization/comments/71gnlr/histomap_creator/", 
            "score": 5, 
            "selftext": "What I'm looking for is a way to visualize several projects of different timeframes simultaneously.  The hours spent on each project fluctuate with their individual deadlines and each project has its own start and end date.  I really see a linear timeline similar to the infamous Histomap as a great solution.  Left to right = calendar, up and down (or thickness) = hours expected on each project at that time.\n\nAny project planners I've seen don't compare several projects alongside each other very well.  For 5 or 6 concurrent projects, I want to see how much time will be spent on each project in order to spot potential bottle necks.\n\nAny suggestions for this ability?  Or maybe even an alternative method.", 
            "subreddit": "visualization", 
            "title": "Histomap creator?", 
            "url": "https://www.reddit.com/r/visualization/comments/71gnlr/histomap_creator/"
        }, 
        {
            "author": "epibiostats", 
            "created_utc": 1505959113.0, 
            "domain": "self.visualization", 
            "id": "71g0xh", 
            "is_reddit_media_domain": false, 
            "is_self": true, 
            "is_video": false, 
            "link_flair_css_class": null, 
            "link_flair_text": null, 
            "media": null, 
            "num_comments": 8, 
            "num_crossposts": 0, 
            "permalink": "/r/visualization/comments/71g0xh/best_resources_to_learn_tableau/", 
            "score": 4, 
            "selftext": "", 
            "subreddit": "visualization", 
            "title": "Best resources to learn tableau?", 
            "url": "https://www.reddit.com/r/visualization/comments/71g0xh/best_resources_to_learn_tableau/"
        }, 
        {
            "author": "Geographist", 
            "created_utc": 1505946833.0, 
            "domain": "visualisingdata.com", 
            "id": "71et46", 
            "is_reddit_media_domain": false, 
            "is_self": false, 
            "is_video": false, 
            "link_flair_css_class": null, 
            "link_flair_text": null, 
            "media": null, 
            "num_comments": 2, 
            "num_crossposts": 0, 
            "permalink": "/r/visualization/comments/71et46/my_reddit_ama_for_rdataisbeautiful/", 
            "score": 7, 
            "selftext": "", 
            "subreddit": "visualization", 
            "title": "My Reddit AMA for r/dataisbeautiful", 
            "url": "http://www.visualisingdata.com/2017/09/reddit-ama-rdataisbeautiful/"
        }, 
        {
            "author": "Socrato", 
            "created_utc": 1505930476.0, 
            "domain": "self.visualization", 
            "id": "71cwfm", 
            "is_reddit_media_domain": false, 
            "is_self": true, 
            "is_video": false, 
            "link_flair_css_class": null, 
            "link_flair_text": null, 
            "media": null, 
            "num_comments": 1, 
            "num_crossposts": 0, 
            "permalink": "/r/visualization/comments/71cwfm/what_the_name_of_the_viz_i_want/", 
            "score": 3, 
            "selftext": "I'm sorry everyone, I hate these posts but I'm turning up nothing with google.\n\nI want essentially a [force directed graph](https://bl.ocks.org/mbostock/4062045), but without edges and to illustrate time series group membership/movement. \n\nI have a cohort I want to illustrate how they move through membership in roughly 10 different groups across a set of roughly 60 periods. I'd like each individual to be represented as a node which has a velocity applied when membership changes and nodes collide to give a \"fluidity\" to their movement.  And group \"centers\" are spread apart to show the clustering.\n\nI know this exists, I've seen a few d3 implementations before, but right now I can't figure out what to google to get me back to those examples.\n\nBonus points if anyone knows a python framework that includes this type of viz.\n\nAny help would be tremendous! Thanks!\n\nEDIT: Here is the visualization I've been thinking of. https://flowingdata.com/2015/12/15/a-day-in-the-life-of-americans/\nThe viz itself is contained in an iframe with the source code found here: http://flowingdata.com/projects/2015/timeuse-simulation/\n\nI've got my work cut out for me! Thanks all", 
            "subreddit": "visualization", 
            "title": "What the name of the viz I want?", 
            "url": "https://www.reddit.com/r/visualization/comments/71cwfm/what_the_name_of_the_viz_i_want/"
        }, 
        {
            "author": "Geographist", 
            "created_utc": 1505918009.0, 
            "domain": "visualisingdata.com", 
            "id": "71bgk7", 
            "is_reddit_media_domain": false, 
            "is_self": false, 
            "is_video": false, 
            "link_flair_css_class": null, 
            "link_flair_text": null, 
            "media": null, 
            "num_comments": 0, 
            "num_crossposts": 0, 
            "permalink": "/r/visualization/comments/71bgk7/best_of_the_visualisation_web_july_2017/", 
            "score": 2, 
            "selftext": "", 
            "subreddit": "visualization", 
            "title": "Best of the visualisation web\u2026 July 2017", 
            "url": "http://www.visualisingdata.com/2017/09/best-visualisation-web-july-2017/"
        }, 
        {
            "author": "Balvinder_123", 
            "created_utc": 1505835290.0, 
            "domain": "youtu.be", 
            "id": "713ro5", 
            "is_reddit_media_domain": false, 
            "is_self": false, 
            "is_video": false, 
            "link_flair_css_class": null, 
            "link_flair_text": null, 
            "media": {
                "oembed": {
                    "author_name": "Singh Gaming & tech", 
                    "author_url": "https://www.youtube.com/channel/UCNCURzLSlN5n1-MPv3xZDyg", 
                    "height": 338, 
                    "html": "<iframe width=\"600\" height=\"338\" src=\"https://www.youtube.com/embed/iSoa732zzKI?feature=oembed\" frameborder=\"0\" allowfullscreen></iframe>", 
                    "provider_name": "YouTube", 
                    "provider_url": "https://www.youtube.com/", 
                    "thumbnail_height": 360, 
                    "thumbnail_url": "https://i.ytimg.com/vi/iSoa732zzKI/hqdefault.jpg", 
                    "thumbnail_width": 480, 
                    "title": "NCS: Colors [Album Mix] bass boosted with new visualiser", 
                    "type": "video", 
                    "version": "1.0", 
                    "width": 600
                }, 
                "type": "youtube.com"
            }, 
            "num_comments": 1, 
            "num_crossposts": 0, 
            "permalink": "/r/visualization/comments/713ro5/new_spectrum_of_ncs_colors_album_mix_bass_boosted/", 
            "score": 0, 
            "selftext": "", 
            "subreddit": "visualization", 
            "title": "New spectrum Of NCS: Colors [Album Mix] bass boosted", 
            "url": "https://youtu.be/iSoa732zzKI"
        }, 
        {
            "author": "EinFichtenbaum", 
            "created_utc": 1505748799.0, 
            "domain": "visual.ly", 
            "id": "70vrne", 
            "is_reddit_media_domain": false, 
            "is_self": false, 
            "is_video": false, 
            "link_flair_css_class": null, 
            "link_flair_text": null, 
            "media": null, 
            "num_comments": 3, 
            "num_crossposts": 0, 
            "permalink": "/r/visualization/comments/70vrne/data_viz_for_traffic_fatalities_in_the_us_since/", 
            "score": 12, 
            "selftext": "", 
            "subreddit": "visualization", 
            "title": "Data Viz for traffic fatalities in the US since 1900", 
            "url": "https://visual.ly/community/Infographics/transportation/traffic-fatalities-1900-united-states"
        }, 
        {
            "author": "ReactDOM", 
            "created_utc": 1505695357.0, 
            "domain": "reactdom.com", 
            "id": "70riua", 
            "is_reddit_media_domain": false, 
            "is_self": false, 
            "is_video": false, 
            "link_flair_css_class": null, 
            "link_flair_text": null, 
            "media": null, 
            "num_comments": 0, 
            "num_crossposts": 2, 
            "permalink": "/r/visualization/comments/70riua/make_epic_visualizations_from_these_d3js/", 
            "score": 15, 
            "selftext": "", 
            "subreddit": "visualization", 
            "title": "Make epic visualizations from these D3.js tutorials & books", 
            "url": "https://reactdom.com/blog/d3js-books"
        }, 
        {
            "author": "austingamer2811", 
            "created_utc": 1505680971.0, 
            "domain": "youtube.com", 
            "id": "70q45e", 
            "is_reddit_media_domain": false, 
            "is_self": false, 
            "is_video": false, 
            "link_flair_css_class": null, 
            "link_flair_text": null, 
            "media": {
                "oembed": {
                    "description": "live stream test", 
                    "height": 338, 
                    "html": "<iframe class=\"embedly-embed\" src=\"//cdn.embedly.com/widgets/media.html?src=http%3A%2F%2Fwww.youtube.com%2Fembed%2F43M10hvOkDc&url=http%3A%2F%2Fwww.youtube.com%2Fwatch%3Fv%3D43M10hvOkDc&image=http%3A%2F%2Fi.ytimg.com%2Fvi%2F43M10hvOkDc%2Fhqdefault.jpg&key=522baf40bd3911e08d854040d3dc5c07&type=text%2Fhtml&schema=youtube\" width=\"600\" height=\"338\" scrolling=\"no\" frameborder=\"0\" allowfullscreen></iframe>", 
                    "provider_name": "YouTube", 
                    "provider_url": "http://youtube.com", 
                    "thumbnail_height": 360, 
                    "thumbnail_url": "http://i.ytimg.com/vi/43M10hvOkDc/hqdefault.jpg", 
                    "thumbnail_width": 480, 
                    "title": "visual test", 
                    "type": "video", 
                    "url": "http://www.youtube.com/watch?v=43M10hvOkDc", 
                    "version": "1.0", 
                    "width": 600
                }, 
                "type": "youtube.com"
            }, 
            "num_comments": 1, 
            "num_crossposts": 0, 
            "permalink": "/r/visualization/comments/70q45e/dmt_visual_test/", 
            "score": 1, 
            "selftext": "", 
            "subreddit": "visualization", 
            "title": "dmt visual test", 
            "url": "https://www.youtube.com/attribution_link?a=dynkUJWU0qo&u=%2Fwatch%3Fv%3D43M10hvOkDc%26feature%3Dshare"
        }, 
        {
            "author": "Balvinder_123", 
            "created_utc": 1505636979.0, 
            "domain": "youtu.be", 
            "id": "70mdxt", 
            "is_reddit_media_domain": false, 
            "is_self": false, 
            "is_video": false, 
            "link_flair_css_class": null, 
            "link_flair_text": null, 
            "media": {
                "oembed": {
                    "author_name": "Singh Gaming & tech", 
                    "author_url": "https://www.youtube.com/channel/UCNCURzLSlN5n1-MPv3xZDyg", 
                    "height": 338, 
                    "html": "<iframe width=\"600\" height=\"338\" src=\"https://www.youtube.com/embed/mBRLD1JVNAU?feature=oembed\" frameborder=\"0\" allowfullscreen></iframe>", 
                    "provider_name": "YouTube", 
                    "provider_url": "https://www.youtube.com/", 
                    "thumbnail_height": 360, 
                    "thumbnail_url": "https://i.ytimg.com/vi/mBRLD1JVNAU/hqdefault.jpg", 
                    "thumbnail_width": 480, 
                    "title": "TARI & Yix - Bliss [NCS Release] bass boosted with new visualiser", 
                    "type": "video", 
                    "version": "1.0", 
                    "width": 600
                }, 
                "type": "youtube.com"
            }, 
            "num_comments": 0, 
            "num_crossposts": 0, 
            "permalink": "/r/visualization/comments/70mdxt/new_visualiser_tari_yix_bliss_ncs_release_bass/", 
            "score": 0, 
            "selftext": "", 
            "subreddit": "visualization", 
            "title": "New visualiser TARI & Yix - Bliss [NCS Release] bass boosted", 
            "url": "https://youtu.be/mBRLD1JVNAU"
        }, 
        {
            "author": "Balvinder_123", 
            "created_utc": 1505631318.0, 
            "domain": "youtu.be", 
            "id": "70m3a8", 
            "is_reddit_media_domain": false, 
            "is_self": false, 
            "is_video": false, 
            "link_flair_css_class": null, 
            "link_flair_text": null, 
            "media": {
                "oembed": {
                    "author_name": "Singh Gaming & tech", 
                    "author_url": "https://www.youtube.com/channel/UCNCURzLSlN5n1-MPv3xZDyg", 
                    "height": 338, 
                    "html": "<iframe width=\"600\" height=\"338\" src=\"https://www.youtube.com/embed/p8bhT15QKCM?feature=oembed\" frameborder=\"0\" allowfullscreen></iframe>", 
                    "provider_name": "YouTube", 
                    "provider_url": "https://www.youtube.com/", 
                    "thumbnail_height": 360, 
                    "thumbnail_url": "https://i.ytimg.com/vi/p8bhT15QKCM/hqdefault.jpg", 
                    "thumbnail_width": 480, 
                    "title": "Syn Cole - Feel Good[Bass Boosted] with new visualiser.", 
                    "type": "video", 
                    "version": "1.0", 
                    "width": 600
                }, 
                "type": "youtube.com"
            }, 
            "num_comments": 0, 
            "num_crossposts": 0, 
            "permalink": "/r/visualization/comments/70m3a8/new_visualiser_syn_cole_feel_goodbass_boosted/", 
            "score": 0, 
            "selftext": "", 
            "subreddit": "visualization", 
            "title": "New visualiser -Syn Cole - Feel Good[Bass Boosted]", 
            "url": "https://youtu.be/p8bhT15QKCM"
        }, 
        {
            "author": "SamL214", 
            "created_utc": 1505601423.0, 
            "domain": "self.visualization", 
            "id": "70jw71", 
            "is_reddit_media_domain": false, 
            "is_self": true, 
            "is_video": false, 
            "link_flair_css_class": null, 
            "link_flair_text": null, 
            "media": null, 
            "num_comments": 0, 
            "num_crossposts": 0, 
            "permalink": "/r/visualization/comments/70jw71/looking_for_any_visualizations_of_earth_53_mya/", 
            "score": 1, 
            "selftext": "I want to visualize more accurate migrations of early hominids and then humans(500-200kya) but I'm having trouble finding any visuals related to progression or regression of oceans/shorelines. Which I think would be super important. \n\nThanks!", 
            "subreddit": "visualization", 
            "title": "Looking for any visualizations of earth 5.3 mya.", 
            "url": "https://www.reddit.com/r/visualization/comments/70jw71/looking_for_any_visualizations_of_earth_53_mya/"
        }, 
        {
            "author": "Balvinder_123", 
            "created_utc": 1505534642.0, 
            "domain": "youtu.be", 
            "id": "70evyu", 
            "is_reddit_media_domain": false, 
            "is_self": false, 
            "is_video": false, 
            "link_flair_css_class": null, 
            "link_flair_text": null, 
            "media": {
                "oembed": {
                    "author_name": "Singh Gaming & tech", 
                    "author_url": "https://www.youtube.com/channel/UCNCURzLSlN5n1-MPv3xZDyg", 
                    "height": 338, 
                    "html": "<iframe width=\"600\" height=\"338\" src=\"https://www.youtube.com/embed/U7WehPeeliE?feature=oembed\" frameborder=\"0\" allowfullscreen></iframe>", 
                    "provider_name": "YouTube", 
                    "provider_url": "https://www.youtube.com/", 
                    "thumbnail_height": 360, 
                    "thumbnail_url": "https://i.ytimg.com/vi/U7WehPeeliE/hqdefault.jpg", 
                    "thumbnail_width": 480, 
                    "title": "Halcyon - Runaway (feat. Valentina Franco)(lyrics)", 
                    "type": "video", 
                    "version": "1.0", 
                    "width": 600
                }, 
                "type": "youtube.com"
            }, 
            "num_comments": 1, 
            "num_crossposts": 0, 
            "permalink": "/r/visualization/comments/70evyu/halcyon_runaway_feat_valentina_francolyrics/", 
            "score": 0, 
            "selftext": "", 
            "subreddit": "visualization", 
            "title": "Halcyon - Runaway (feat. Valentina Franco)(lyrics)", 
            "url": "https://youtu.be/U7WehPeeliE"
        }, 
        {
            "author": "acousticwave", 
            "created_utc": 1505517132.0, 
            "domain": "self.visualization", 
            "id": "70dhuj", 
            "is_reddit_media_domain": false, 
            "is_self": true, 
            "is_video": false, 
            "link_flair_css_class": null, 
            "link_flair_text": null, 
            "media": null, 
            "num_comments": 1, 
            "num_crossposts": 0, 
            "permalink": "/r/visualization/comments/70dhuj/plotly_multiple_subplots_help/", 
            "score": 2, 
            "selftext": "Hi guys,\n\nI'm trying to generate a series of subplots (4 rows, 2 columns) using plotly, and have been looking at the documentation here\n\nhttps://plot.ly/python/subplots/\n\nunder the \"multiple subplots\" heading. In my opinion the syntax and lengths one has to go through to generate multiple subplots is fucking retarded. In your experience, is there an easier way to do this rather than one long giant column of trace and layout calls?\n", 
            "subreddit": "visualization", 
            "title": "Plot.ly Multiple Subplots Help", 
            "url": "https://www.reddit.com/r/visualization/comments/70dhuj/plotly_multiple_subplots_help/"
        }, 
        {
            "author": "neaturenut", 
            "created_utc": 1505507309.0, 
            "domain": "self.visualization", 
            "id": "70ciu2", 
            "is_reddit_media_domain": false, 
            "is_self": true, 
            "is_video": false, 
            "link_flair_css_class": null, 
            "link_flair_text": null, 
            "media": null, 
            "num_comments": 1, 
            "num_crossposts": 0, 
            "permalink": "/r/visualization/comments/70ciu2/question_software_for_embedding_links_or_hotspots/", 
            "score": 1, 
            "selftext": "I am trying to construct a virtual field trip for a large screen display. I am curious if anyone has any experience with software that will let me embed clickable links on an image. My vision is that a panoramic image will be displayed on the screen with areas that students would be able to click or touch regions that would provide supplemental information. \n\nThanks in advance for the help!", 
            "subreddit": "visualization", 
            "title": "[Question]: Software for embedding links or hotspots on images", 
            "url": "https://www.reddit.com/r/visualization/comments/70ciu2/question_software_for_embedding_links_or_hotspots/"
        }, 
        {
            "author": "sjl127", 
            "created_utc": 1505409216.0, 
            "domain": "self.visualization", 
            "id": "703nug", 
            "is_reddit_media_domain": false, 
            "is_self": true, 
            "is_video": false, 
            "link_flair_css_class": null, 
            "link_flair_text": null, 
            "media": null, 
            "num_comments": 5, 
            "num_crossposts": 0, 
            "permalink": "/r/visualization/comments/703nug/is_is_possible_to_graphically_display_data_points/", 
            "score": 5, 
            "selftext": "How can I relate, graphically, causes, reactions, and effects?\n\n    Cause 1         Reaction 1              Effect 1\n    Cause 2         Reaction 2              Effect 2\n    \nData gathered is severity expressed as NONE SLIGHT MODERATE SEVERE.\n                 Extensiveness expressed as local vs. generalized.\n                 \n                 \nIs there a way to graphically represent these? On a plot somehow?", 
            "subreddit": "visualization", 
            "title": "Is is possible to graphically display data points with two variables?", 
            "url": "https://www.reddit.com/r/visualization/comments/703nug/is_is_possible_to_graphically_display_data_points/"
        }, 
        {
            "author": "bradleysara31", 
            "created_utc": 1505357520.0, 
            "domain": "abc.net.au", 
            "id": "6zzkik", 
            "is_reddit_media_domain": false, 
            "is_self": false, 
            "is_video": false, 
            "link_flair_css_class": null, 
            "link_flair_text": null, 
            "media": null, 
            "num_comments": 3, 
            "num_crossposts": 0, 
            "permalink": "/r/visualization/comments/6zzkik/how_australians_think_about_samesex_marriage/", 
            "score": 16, 
            "selftext": "", 
            "subreddit": "visualization", 
            "title": "How Australians think about same-sex marriage, mapped", 
            "url": "http://www.abc.net.au/news/2017-09-13/same-sex-marriage-support-map-vote-compass/8788978?smid=Page:%20ABC%20News-Facebook_Organic&WT.tsrc=Facebook_Organic&sf113504485=1"
        }, 
        {
            "author": "McKellMyBelle", 
            "created_utc": 1505344713.0, 
            "domain": "self.visualization", 
            "id": "6zye7j", 
            "is_reddit_media_domain": false, 
            "is_self": true, 
            "is_video": false, 
            "link_flair_css_class": null, 
            "link_flair_text": null, 
            "media": null, 
            "num_comments": 2, 
            "num_crossposts": 0, 
            "permalink": "/r/visualization/comments/6zye7j/opinions_needed/", 
            "score": 1, 
            "selftext": "I need to display trending data for 24 different categories. A line graph is a spaghetti bowl. A stacked bar chart is misleading. I need to get creative but I'm at a loss. Any suggestions?", 
            "subreddit": "visualization", 
            "title": "Opinions needed", 
            "url": "https://www.reddit.com/r/visualization/comments/6zye7j/opinions_needed/"
        }, 
        {
            "author": "gtam_ds", 
            "created_utc": 1505333631.0, 
            "domain": "content.pivotal.io", 
            "id": "6zx7w4", 
            "is_reddit_media_domain": false, 
            "is_self": false, 
            "is_video": false, 
            "link_flair_css_class": null, 
            "link_flair_text": null, 
            "media": null, 
            "num_comments": 0, 
            "num_crossposts": 0, 
            "permalink": "/r/visualization/comments/6zx7w4/citi_bike_trips_in_nyc/", 
            "score": 3, 
            "selftext": "", 
            "subreddit": "visualization", 
            "title": "Citi Bike Trips in NYC", 
            "url": "https://content.pivotal.io/blog/using-sparkr-to-analyze-citi-bike-data"
        }, 
        {
            "author": "rpgove", 
            "created_utc": 1505319709.0, 
            "domain": "twosixlabs.com", 
            "id": "6zvmt8", 
            "is_reddit_media_domain": false, 
            "is_self": false, 
            "is_video": false, 
            "link_flair_css_class": null, 
            "link_flair_text": null, 
            "media": null, 
            "num_comments": 2, 
            "num_crossposts": 0, 
            "permalink": "/r/visualization/comments/6zvmt8/6_ways_to_visualize_graphs/", 
            "score": 25, 
            "selftext": "", 
            "subreddit": "visualization", 
            "title": "6 Ways to Visualize Graphs", 
            "url": "https://www.twosixlabs.com/6-ways-visualize-graphs/"
        }, 
        {
            "author": "Geographist", 
            "created_utc": 1505298363.0, 
            "domain": "visualisingdata.com", 
            "id": "6ztoji", 
            "is_reddit_media_domain": false, 
            "is_self": false, 
            "is_video": false, 
            "link_flair_css_class": null, 
            "link_flair_text": null, 
            "media": null, 
            "num_comments": 0, 
            "num_crossposts": 0, 
            "permalink": "/r/visualization/comments/6ztoji/the_little_of_visualisation_design_part_43/", 
            "score": 2, 
            "selftext": "", 
            "subreddit": "visualization", 
            "title": "The little of visualisation design: Part 43", 
            "url": "http://www.visualisingdata.com/2017/09/little-visualisation-design-part-43/"
        }, 
        {
            "author": "datahero4u", 
            "created_utc": 1505253814.0, 
            "domain": "youtube.com", 
            "id": "6zqaz6", 
            "is_reddit_media_domain": false, 
            "is_self": false, 
            "is_video": false, 
            "link_flair_css_class": null, 
            "link_flair_text": null, 
            "media": {
                "oembed": {
                    "author_name": "PowerMapBI", 
                    "author_url": "https://www.youtube.com/user/PowerMapBI", 
                    "height": 338, 
                    "html": "<iframe width=\"600\" height=\"338\" src=\"https://www.youtube.com/embed/CRsrt656xMs?feature=oembed\" frameborder=\"0\" allowfullscreen></iframe>", 
                    "provider_name": "YouTube", 
                    "provider_url": "https://www.youtube.com/", 
                    "thumbnail_height": 360, 
                    "thumbnail_url": "https://i.ytimg.com/vi/CRsrt656xMs/hqdefault.jpg", 
                    "thumbnail_width": 480, 
                    "title": "World War II Military Historical Timeline in MS Excel Power Map", 
                    "type": "video", 
                    "version": "1.0", 
                    "width": 600
                }, 
                "type": "youtube.com"
            }, 
            "num_comments": 2, 
            "num_crossposts": 0, 
            "permalink": "/r/visualization/comments/6zqaz6/world_war_2_military_historical_timeline_in_ms/", 
            "score": 7, 
            "selftext": "", 
            "subreddit": "visualization", 
            "title": "World War 2 Military Historical Timeline in MS Excel Power Map", 
            "url": "https://www.youtube.com/watch?v=CRsrt656xMs"
        }, 
        {
            "author": "localfield", 
            "created_utc": 1505176204.0, 
            "domain": "srcole.github.io", 
            "id": "6zjiev", 
            "is_reddit_media_domain": false, 
            "is_self": false, 
            "is_video": false, 
            "link_flair_css_class": null, 
            "link_flair_text": null, 
            "media": null, 
            "num_comments": 1, 
            "num_crossposts": 0, 
            "permalink": "/r/visualization/comments/6zjiev/bokeh_interactive_plot_showing_time_to_retirement/", 
            "score": 6, 
            "selftext": "", 
            "subreddit": "visualization", 
            "title": "Bokeh interactive plot showing time to retirement for different savings plans.", 
            "url": "https://srcole.github.io/2017/09/09/retirement/"
        }, 
        {
            "author": "Delta4s2Cyclone", 
            "created_utc": 1505160924.0, 
            "domain": "kaggle.com", 
            "id": "6zhzkd", 
            "is_reddit_media_domain": false, 
            "is_self": false, 
            "is_video": false, 
            "link_flair_css_class": null, 
            "link_flair_text": null, 
            "media": null, 
            "num_comments": 5, 
            "num_crossposts": 0, 
            "permalink": "/r/visualization/comments/6zhzkd/the_most_dangerous_places_to_work_in_the_usa/", 
            "score": 6, 
            "selftext": "", 
            "subreddit": "visualization", 
            "title": "The Most Dangerous Places to Work in the USA", 
            "url": "https://www.kaggle.com/pranav84/the-most-dangerous-places-to-work-in-the-usa"
        }, 
        {
            "author": "dataphysicist", 
            "created_utc": 1504910569.0, 
            "domain": "dataquest.io", 
            "id": "6yy5z4", 
            "is_reddit_media_domain": false, 
            "is_self": false, 
            "is_video": false, 
            "link_flair_css_class": null, 
            "link_flair_text": null, 
            "media": null, 
            "num_comments": 1, 
            "num_crossposts": 0, 
            "permalink": "/r/visualization/comments/6yy5z4/how_to_generate_fivethirtyeight_graphs_in_python/", 
            "score": 31, 
            "selftext": "", 
            "subreddit": "visualization", 
            "title": "How to Generate FiveThirtyEight Graphs in Python", 
            "url": "https://www.dataquest.io/blog/making-538-plots/"
        }, 
        {
            "author": "EinFichtenbaum", 
            "created_utc": 1504898670.0, 
            "domain": "visual.ly", 
            "id": "6ywz45", 
            "is_reddit_media_domain": false, 
            "is_self": false, 
            "is_video": false, 
            "link_flair_css_class": null, 
            "link_flair_text": null, 
            "media": null, 
            "num_comments": 1, 
            "num_crossposts": 0, 
            "permalink": "/r/visualization/comments/6ywz45/dataviz_for_the_top_15_mostvisited_domains_in_the/", 
            "score": 2, 
            "selftext": "", 
            "subreddit": "visualization", 
            "title": "DataViz for The Top 15 Most-Visited Domains in the U.S.", 
            "url": "https://visual.ly/community/Infographics/computers/top-15-most-visited-domains-us-and-their-key-metrics"
        }, 
        {
            "author": "paulwaker512", 
            "created_utc": 1504776831.0, 
            "domain": "srushtiviz.com", 
            "id": "6ym5ib", 
            "is_reddit_media_domain": false, 
            "is_self": false, 
            "is_video": false, 
            "link_flair_css_class": null, 
            "link_flair_text": null, 
            "media": null, 
            "num_comments": 0, 
            "num_crossposts": 0, 
            "permalink": "/r/visualization/comments/6ym5ib/why_should_you_show_your_product_before_it_is/", 
            "score": 1, 
            "selftext": "", 
            "subreddit": "visualization", 
            "title": "Why should you show your product before it is manufactured! The power and importance of product visualization.", 
            "url": "http://srushtiviz.com/blog/why-should-you-show-your-product-before-it-is-manufactured-the-power-and-importance-of-product-visualization/"
        }, 
        {
            "author": "PassiveAgressiveHobo", 
            "created_utc": 1504733360.0, 
            "domain": "youtube.com", 
            "id": "6yio3v", 
            "is_reddit_media_domain": false, 
            "is_self": false, 
            "is_video": false, 
            "link_flair_css_class": null, 
            "link_flair_text": null, 
            "media": {
                "oembed": {
                    "author_name": "Heavybit", 
                    "author_url": "https://www.youtube.com/user/HeavybitIndustries", 
                    "height": 338, 
                    "html": "<iframe width=\"600\" height=\"338\" src=\"https://www.youtube.com/embed/jWpI8qzqNHk?feature=oembed\" frameborder=\"0\" allowfullscreen></iframe>", 
                    "provider_name": "YouTube", 
                    "provider_url": "https://www.youtube.com/", 
                    "thumbnail_height": 360, 
                    "thumbnail_url": "https://i.ytimg.com/vi/jWpI8qzqNHk/hqdefault.jpg", 
                    "thumbnail_width": 480, 
                    "title": "Justin Reynolds: Intuition Engineering at Netflix with Vizceral", 
                    "type": "video", 
                    "version": "1.0", 
                    "width": 600
                }, 
                "type": "youtube.com"
            }, 
            "num_comments": 1, 
            "num_crossposts": 0, 
            "permalink": "/r/visualization/comments/6yio3v/intuition_engineering_at_netflix_with_vizceral/", 
            "score": 4, 
            "selftext": "", 
            "subreddit": "visualization", 
            "title": "Intuition Engineering at Netflix with Vizceral", 
            "url": "https://www.youtube.com/watch?v=jWpI8qzqNHk"
        }, 
        {
            "author": "maxmacks", 
            "created_utc": 1504707124.0, 
            "domain": "self.visualization", 
            "id": "6yfusr", 
            "is_reddit_media_domain": false, 
            "is_self": true, 
            "is_video": false, 
            "link_flair_css_class": null, 
            "link_flair_text": null, 
            "media": null, 
            "num_comments": 0, 
            "num_crossposts": 0, 
            "permalink": "/r/visualization/comments/6yfusr/looking_to_visualise_animated_movements_of/", 
            "score": 6, 
            "selftext": "Many thanks for any help. looking for both paid and free ideas. groups include police, rioters and pedestrians. It would also be useful if I could indicate certain events and locations, and the time and date of what was happening. ", 
            "subreddit": "visualization", 
            "title": "Looking to visualise animated movements of rioting groups during a riot on a map of the local area. What software would be good for this?", 
            "url": "https://www.reddit.com/r/visualization/comments/6yfusr/looking_to_visualise_animated_movements_of/"
        }, 
        {
            "author": "jmerlinb", 
            "created_utc": 1504700467.0, 
            "domain": "self.visualization", 
            "id": "6yfa27", 
            "is_reddit_media_domain": false, 
            "is_self": true, 
            "is_video": false, 
            "link_flair_css_class": null, 
            "link_flair_text": null, 
            "media": null, 
            "num_comments": 11, 
            "num_crossposts": 0, 
            "permalink": "/r/visualization/comments/6yfa27/how_would_one_go_about_creating_a_stream_graph/", 
            "score": 3, 
            "selftext": "Example of a [stream graph](https://www.google.co.uk/search?q=stream+graph&safe=strict&rlz=1C5CHFA_enGB744GB744&source=lnms&tbm=isch&sa=X&ved=0ahUKEwiK9_XtxZDWAhVsIcAKHY3BB44Q_AUICigB&biw=1440&bih=826&dpr=2)\n\nI've searched all over the web, but can't seem to find a solid guide on how to create one. \n\nAny ideas?", 
            "subreddit": "visualization", 
            "title": "How would one go about creating a *stream graph*?", 
            "url": "https://www.reddit.com/r/visualization/comments/6yfa27/how_would_one_go_about_creating_a_stream_graph/"
        }, 
        {
            "author": "juanosborne", 
            "created_utc": 1504289958.0, 
            "domain": "juanosborne.com", 
            "id": "6xgedl", 
            "is_reddit_media_domain": false, 
            "is_self": false, 
            "is_video": false, 
            "link_flair_css_class": null, 
            "link_flair_text": null, 
            "media": null, 
            "num_comments": 14, 
            "num_crossposts": 0, 
            "permalink": "/r/visualization/comments/6xgedl/10300_most_used_words_in_trump_30000_tweets_and/", 
            "score": 23, 
            "selftext": "", 
            "subreddit": "visualization", 
            "title": "10.300 Most used words in Trump 30.000 Tweets and Retweets, from 2009 to 2017.", 
            "url": "http://www.juanosborne.com/2017/09/trump-on-his-tweets/"
        }, 
        {
            "author": "Geographist", 
            "created_utc": 1504284087.0, 
            "domain": "visualisingdata.com", 
            "id": "6xfqo7", 
            "is_reddit_media_domain": false, 
            "is_self": false, 
            "is_video": false, 
            "link_flair_css_class": null, 
            "link_flair_text": null, 
            "media": null, 
            "num_comments": 1, 
            "num_crossposts": 0, 
            "permalink": "/r/visualization/comments/6xfqo7/the_problems_with_barc_charts/", 
            "score": 1, 
            "selftext": "", 
            "subreddit": "visualization", 
            "title": "The problems with b'arc charts", 
            "url": "http://www.visualisingdata.com/2017/09/problems-barc-charts/"
        }, 
        {
            "author": "mkalygin", 
            "created_utc": 1504279535.0, 
            "domain": "tehcookies.com", 
            "id": "6xf8e7", 
            "is_reddit_media_domain": false, 
            "is_self": false, 
            "is_video": false, 
            "link_flair_css_class": null, 
            "link_flair_text": null, 
            "media": null, 
            "num_comments": 1, 
            "num_crossposts": 0, 
            "permalink": "/r/visualization/comments/6xf8e7/demo_how_much_developers_earn/", 
            "score": 13, 
            "selftext": "", 
            "subreddit": "visualization", 
            "title": "Demo: How much developers earn?", 
            "url": "http://tehcookies.com/devsalaries/"
        }
    ], 
    "subreddit_creation_utc": 1206436279.0, 
    "subscribers": 19479, 
    "title": "Visualization", 
    "title_word_count_occurrences": {
        "google": 1, 
        "netflix": 1, 
        "python": 2, 
        "tex": 1
    }, 
    "top_score_submissions": [
        {
            "author": "dataphysicist", 
            "created_utc": 1504910569.0, 
            "domain": "dataquest.io", 
            "id": "6yy5z4", 
            "is_reddit_media_domain": false, 
            "is_self": false, 
            "is_video": false, 
            "link_flair_css_class": null, 
            "link_flair_text": null, 
            "media": null, 
            "num_comments": 1, 
            "num_crossposts": 0, 
            "permalink": "/r/visualization/comments/6yy5z4/how_to_generate_fivethirtyeight_graphs_in_python/", 
            "score": 31, 
            "selftext": "", 
            "subreddit": "visualization", 
            "title": "How to Generate FiveThirtyEight Graphs in Python", 
            "url": "https://www.dataquest.io/blog/making-538-plots/"
        }, 
        {
            "author": "rino_design", 
            "created_utc": 1506530460.0, 
            "domain": "datavizcatalogue.com", 
            "id": "72tibw", 
            "is_reddit_media_domain": false, 
            "is_self": false, 
            "is_video": false, 
            "link_flair_css_class": null, 
            "link_flair_text": null, 
            "media": null, 
            "num_comments": 4, 
            "num_crossposts": 0, 
            "permalink": "/r/visualization/comments/72tibw/heres_some_unusual_box_plot_variations_you_might/", 
            "score": 29, 
            "selftext": "", 
            "subreddit": "visualization", 
            "title": "Here's some unusual Box Plot variations you might not know about...", 
            "url": "http://datavizcatalogue.com/blog/box-plot-variations/"
        }, 
        {
            "author": "kpei1hunnit", 
            "created_utc": 1506448340.0, 
            "domain": "imgur.com", 
            "id": "72m3tl", 
            "is_reddit_media_domain": false, 
            "is_self": false, 
            "is_video": false, 
            "link_flair_css_class": null, 
            "link_flair_text": null, 
            "media": {
                "oembed": {
                    "description": "Imgur: The most awesome images on the Internet.", 
                    "height": 550, 
                    "html": "<iframe class=\"embedly-embed\" src=\"//cdn.embedly.com/widgets/media.html?src=%2F%2Fimgur.com%2Fa%2F6JhTt%2Fembed&url=https%3A%2F%2Fimgur.com%2Fa%2F6JhTt&image=https%3A%2F%2Fi.imgur.com%2FwsOJdIg.jpg%3Ffb&key=522baf40bd3911e08d854040d3dc5c07&type=text%2Fhtml&schema=imgur\" width=\"550\" height=\"550\" scrolling=\"no\" frameborder=\"0\" allowfullscreen></iframe>", 
                    "provider_name": "Imgur", 
                    "provider_url": "http://imgur.com", 
                    "thumbnail_height": 315, 
                    "thumbnail_url": "https://i.imgur.com/wsOJdIg.jpg?fb", 
                    "thumbnail_width": 600, 
                    "title": "Heatmaps of Attacking Frequency", 
                    "type": "rich", 
                    "version": "1.0", 
                    "width": 550
                }, 
                "type": "imgur.com"
            }, 
            "num_comments": 5, 
            "num_crossposts": 0, 
            "permalink": "/r/visualization/comments/72m3tl/a_heatmap_of_counterstrike_players_positioning/", 
            "score": 29, 
            "selftext": "", 
            "subreddit": "visualization", 
            "title": "A Heatmap of Counter-Strike Player's Positioning over 1000 recorded Matchmaking games [OC]", 
            "url": "https://imgur.com/a/6JhTt"
        }, 
        {
            "author": "rpgove", 
            "created_utc": 1505319709.0, 
            "domain": "twosixlabs.com", 
            "id": "6zvmt8", 
            "is_reddit_media_domain": false, 
            "is_self": false, 
            "is_video": false, 
            "link_flair_css_class": null, 
            "link_flair_text": null, 
            "media": null, 
            "num_comments": 2, 
            "num_crossposts": 0, 
            "permalink": "/r/visualization/comments/6zvmt8/6_ways_to_visualize_graphs/", 
            "score": 25, 
            "selftext": "", 
            "subreddit": "visualization", 
            "title": "6 Ways to Visualize Graphs", 
            "url": "https://www.twosixlabs.com/6-ways-visualize-graphs/"
        }, 
        {
            "author": "juanosborne", 
            "created_utc": 1504289958.0, 
            "domain": "juanosborne.com", 
            "id": "6xgedl", 
            "is_reddit_media_domain": false, 
            "is_self": false, 
            "is_video": false, 
            "link_flair_css_class": null, 
            "link_flair_text": null, 
            "media": null, 
            "num_comments": 14, 
            "num_crossposts": 0, 
            "permalink": "/r/visualization/comments/6xgedl/10300_most_used_words_in_trump_30000_tweets_and/", 
            "score": 23, 
            "selftext": "", 
            "subreddit": "visualization", 
            "title": "10.300 Most used words in Trump 30.000 Tweets and Retweets, from 2009 to 2017.", 
            "url": "http://www.juanosborne.com/2017/09/trump-on-his-tweets/"
        }
    ], 
    "total_submissions": 44, 
    "utc_of_data_collection_completion": "2017-10-17 18:47:47", 
    "utc_of_data_collection_start": "2017-10-17 18:47:46"
}