{
    "active_user_count": 9, 
    "advertiser_category": null, 
    "audience_target": "", 
    "avg_comment_num_per_submission": 1, 
    "avg_submission_score": 0, 
    "collection_range_end_unix_timestamp": 1507420800, 
    "collection_range_end_utc": "2017-10-08 00:00:00", 
    "collection_range_start_unix_timestamp": 1506816000, 
    "collection_range_start_utc": "2017-10-01 00:00:00", 
    "description": "Topics about Apache's Hadoop cloud platform and its related ecosystem - Pig, Hive, Cassandra, ZooKeeper\n\n----\nRelated subreddits:\n\n/r/Database\n\n/r/Datamining\n\n/r/BigData\n\n/r/CloudComputing\n\n/r/Nosql\n\n/r/MongoDB\n\n/r/DataSets\n\n/r/Intel\n", 
    "display_name": "hadoop", 
    "domain_occurrences": {
        "self.hadoop": 3, 
        "technewsncareer.com": 1
    }, 
    "id": "2r1e2", 
    "num_external_website_posts": 1, 
    "num_text_posts": 3, 
    "public_description": "", 
    "submissions": [
        {
            "author": "marksteve4", 
            "created_utc": 1507334842.0, 
            "domain": "self.hadoop", 
            "id": "74rmg3", 
            "is_reddit_media_domain": false, 
            "is_self": true, 
            "is_video": false, 
            "link_flair_css_class": null, 
            "link_flair_text": null, 
            "media": null, 
            "num_comments": 1, 
            "num_crossposts": 0, 
            "permalink": "/r/hadoop/comments/74rmg3/what_is_the_difference_between_a_hcatalog_and/", 
            "score": 0, 
            "selftext": "I am new to Hadoop and hive. Wonder what is the difference between these two. Expedition into google land doesn't give me too many results.", 
            "subreddit": "hadoop", 
            "title": "What is the difference between a HCatalog and Metastore in Hive?", 
            "url": "https://www.reddit.com/r/hadoop/comments/74rmg3/what_is_the_difference_between_a_hcatalog_and/"
        }, 
        {
            "author": "sundazefeeling", 
            "created_utc": 1507276372.0, 
            "domain": "self.hadoop", 
            "id": "74m7ev", 
            "is_reddit_media_domain": false, 
            "is_self": true, 
            "is_video": false, 
            "link_flair_css_class": null, 
            "link_flair_text": null, 
            "media": null, 
            "num_comments": 2, 
            "num_crossposts": 0, 
            "permalink": "/r/hadoop/comments/74m7ev/what_operating_system_should_i_use_in_my_virtual/", 
            "score": 1, 
            "selftext": "", 
            "subreddit": "hadoop", 
            "title": "What operating system should I use in my virtual machine so I could run a multi node cluster?", 
            "url": "https://www.reddit.com/r/hadoop/comments/74m7ev/what_operating_system_should_i_use_in_my_virtual/"
        }, 
        {
            "author": "marksteve4", 
            "created_utc": 1507145984.0, 
            "domain": "self.hadoop", 
            "id": "74alr0", 
            "is_reddit_media_domain": false, 
            "is_self": true, 
            "is_video": false, 
            "link_flair_css_class": null, 
            "link_flair_text": null, 
            "media": null, 
            "num_comments": 1, 
            "num_crossposts": 0, 
            "permalink": "/r/hadoop/comments/74alr0/how_can_i_persist_beeline_command_history/", 
            "score": 0, 
            "selftext": "I am using beeline for hive queries. But every time the session ends, I lost my command history. Is there a way to persist it?", 
            "subreddit": "hadoop", 
            "title": "How can I persist beeline command history?", 
            "url": "https://www.reddit.com/r/hadoop/comments/74alr0/how_can_i_persist_beeline_command_history/"
        }, 
        {
            "author": "mihir_kanzariya", 
            "created_utc": 1506928242.0, 
            "domain": "technewsncareer.com", 
            "id": "73rb4e", 
            "is_reddit_media_domain": false, 
            "is_self": false, 
            "is_video": false, 
            "link_flair_css_class": null, 
            "link_flair_text": null, 
            "media": null, 
            "num_comments": 0, 
            "num_crossposts": 0, 
            "permalink": "/r/hadoop/comments/73rb4e/hadoop_hdfs_overview_architecture/", 
            "score": 0, 
            "selftext": "", 
            "subreddit": "hadoop", 
            "title": "Hadoop - HDFS Overview & Architecture", 
            "url": "http://www.technewsncareer.com/2017/09/hadoop-hdfs-overview-architecture.html"
        }
    ], 
    "subreddit_creation_utc": 1246447083.0, 
    "subscribers": 4499, 
    "title": "All about the yellow elephant that powers the cloud", 
    "title_word_count_occurrences": {
        "hadoop": 1
    }, 
    "top_score_submissions": [
        {
            "author": "sundazefeeling", 
            "created_utc": 1507276372.0, 
            "domain": "self.hadoop", 
            "id": "74m7ev", 
            "is_reddit_media_domain": false, 
            "is_self": true, 
            "is_video": false, 
            "link_flair_css_class": null, 
            "link_flair_text": null, 
            "media": null, 
            "num_comments": 2, 
            "num_crossposts": 0, 
            "permalink": "/r/hadoop/comments/74m7ev/what_operating_system_should_i_use_in_my_virtual/", 
            "score": 1, 
            "selftext": "", 
            "subreddit": "hadoop", 
            "title": "What operating system should I use in my virtual machine so I could run a multi node cluster?", 
            "url": "https://www.reddit.com/r/hadoop/comments/74m7ev/what_operating_system_should_i_use_in_my_virtual/"
        }, 
        {
            "author": "marksteve4", 
            "created_utc": 1507334842.0, 
            "domain": "self.hadoop", 
            "id": "74rmg3", 
            "is_reddit_media_domain": false, 
            "is_self": true, 
            "is_video": false, 
            "link_flair_css_class": null, 
            "link_flair_text": null, 
            "media": null, 
            "num_comments": 1, 
            "num_crossposts": 0, 
            "permalink": "/r/hadoop/comments/74rmg3/what_is_the_difference_between_a_hcatalog_and/", 
            "score": 0, 
            "selftext": "I am new to Hadoop and hive. Wonder what is the difference between these two. Expedition into google land doesn't give me too many results.", 
            "subreddit": "hadoop", 
            "title": "What is the difference between a HCatalog and Metastore in Hive?", 
            "url": "https://www.reddit.com/r/hadoop/comments/74rmg3/what_is_the_difference_between_a_hcatalog_and/"
        }, 
        {
            "author": "marksteve4", 
            "created_utc": 1507145984.0, 
            "domain": "self.hadoop", 
            "id": "74alr0", 
            "is_reddit_media_domain": false, 
            "is_self": true, 
            "is_video": false, 
            "link_flair_css_class": null, 
            "link_flair_text": null, 
            "media": null, 
            "num_comments": 1, 
            "num_crossposts": 0, 
            "permalink": "/r/hadoop/comments/74alr0/how_can_i_persist_beeline_command_history/", 
            "score": 0, 
            "selftext": "I am using beeline for hive queries. But every time the session ends, I lost my command history. Is there a way to persist it?", 
            "subreddit": "hadoop", 
            "title": "How can I persist beeline command history?", 
            "url": "https://www.reddit.com/r/hadoop/comments/74alr0/how_can_i_persist_beeline_command_history/"
        }, 
        {
            "author": "mihir_kanzariya", 
            "created_utc": 1506928242.0, 
            "domain": "technewsncareer.com", 
            "id": "73rb4e", 
            "is_reddit_media_domain": false, 
            "is_self": false, 
            "is_video": false, 
            "link_flair_css_class": null, 
            "link_flair_text": null, 
            "media": null, 
            "num_comments": 0, 
            "num_crossposts": 0, 
            "permalink": "/r/hadoop/comments/73rb4e/hadoop_hdfs_overview_architecture/", 
            "score": 0, 
            "selftext": "", 
            "subreddit": "hadoop", 
            "title": "Hadoop - HDFS Overview & Architecture", 
            "url": "http://www.technewsncareer.com/2017/09/hadoop-hdfs-overview-architecture.html"
        }
    ], 
    "total_submissions": 4, 
    "utc_of_data_collection_start": "2017-10-16 18:37:49"
}